auto_digo/__init__.py
auto_digo/auto_digo.py
auto_digo/main.py
auto_digo-0.0.3.dist-info/METADATA
auto_digo-0.0.3.dist-info/WHEEL
auto_digo-0.0.3.dist-info/entry_points.txt
auto_digo-0.0.3.dist-info/top_level.txt
auto_digo-0.0.3.dist-info/RECORD
