Metadata-Version: 2.1
Name: auto-digo
Version: 0.0.3
Summary: automatic ml module
Home-page: UNKNOWN
Author: DiggerWorks
Author-email: kunka8271@gmail.com
License: UNKNOWN
Platform: UNKNOWN
Requires-Dist: argparse
